dedocutils/__init__.py
dedocutils/utils.py
dedocutils/data_structures/__init__.py
dedocutils/data_structures/bbox.py
dedocutils/data_structures/text_with_bbox.py
dedocutils/line_segmentation/__init__.py
dedocutils/line_segmentation/abstract_line_segmenter.py
dedocutils/line_segmentation/clustering_line_segmenter.py
dedocutils/line_segmentation/intersection_line_segmenter.py
dedocutils/preprocessing/__init__.py
dedocutils/preprocessing/abstract_preprocessor.py
dedocutils/preprocessing/adaptive_binarizer.py
dedocutils/preprocessing/skew_corrector.py
dedocutils/text_detection/__init__.py
dedocutils/text_detection/abstract_text_detector.py
dedocutils/text_detection/tesseract_text_detector.py
dedocutils/text_detection/doctr_text_detector/__init__.py
dedocutils/text_detection/doctr_text_detector/doctr_text_detector.py
dedocutils/text_detection/doctr_text_detector/doctr/__init__.py
dedocutils/text_detection/doctr_text_detector/doctr/datasets/__init__.py
dedocutils/text_detection/doctr_text_detector/doctr/datasets/vocabs.py
dedocutils/text_detection/doctr_text_detector/doctr/models/__init__.py
dedocutils/text_detection/doctr_text_detector/doctr/models/_utils.py
dedocutils/text_detection/doctr_text_detector/doctr/models/core.py
dedocutils/text_detection/doctr_text_detector/doctr/models/classification/__init__.py
dedocutils/text_detection/doctr_text_detector/doctr/models/classification/zoo.py
dedocutils/text_detection/doctr_text_detector/doctr/models/classification/predictor/__init__.py
dedocutils/text_detection/doctr_text_detector/doctr/models/classification/predictor/pytorch.py
dedocutils/text_detection/doctr_text_detector/doctr/models/classification/resnet/__init__.py
dedocutils/text_detection/doctr_text_detector/doctr/models/classification/resnet/pytorch.py
dedocutils/text_detection/doctr_text_detector/doctr/models/detection/__init__.py
dedocutils/text_detection/doctr_text_detector/doctr/models/detection/core.py
dedoc_utils-0.3.8.dist-info/LICENSE
dedoc_utils-0.3.8.dist-info/METADATA
dedoc_utils-0.3.8.dist-info/WHEEL
dedoc_utils-0.3.8.dist-info/top_level.txt
dedoc_utils-0.3.8.dist-info/RECORD
