Metadata-Version: 2.1
Name: dedoc-utils
Version: 0.3.8
Summary: Utils for automatic document images processing
Author-email: Dedoc team <dedoc@ispras.ru>
Maintainer-email: Oksana Belyaeva <belyaeva@ispras.ru>, Andrew Perminov <perminov@ispras.ru>, Anastasiya Bogatenkova <bogatenkova.anastasiya@mail.ru>
License: Apache License
Project-URL: homepage, https://github.com/ispras/dedoc-utils
Project-URL: repository, https://github.com/ispras/dedoc-utils
Project-URL: documentation, https://github.com/ispras/dedoc-utils/blob/master/README.md
Project-URL: changelog, https://github.com/ispras/dedoc-utils/blob/master/CHANGELOG.md
Keywords: text detection,text recognition,OCR,deep learning,computer vision
Classifier: Intended Audience :: Developers
Classifier: License :: OSI Approved :: Apache Software License
Classifier: Programming Language :: Python :: 3.8
Classifier: Programming Language :: Python :: 3.9
Classifier: Programming Language :: Python :: 3.10
Classifier: Programming Language :: Python :: 3 :: Only
Requires-Python: >=3.6
License-File: LICENSE
Requires-Dist: numpy<2.0,>=1.22.0
Requires-Dist: opencv-python<=4.6.0.66,>=4.5.5.64
Requires-Dist: pytesseract>=0.3
Requires-Dist: scikit-learn<=1.3.1,>=1.0.2
Provides-Extra: dev
Requires-Dist: importlib-metadata==7.2.1; extra == "dev"
Requires-Dist: build==0.10.0; extra == "dev"
Requires-Dist: twine==4.0.2; extra == "dev"
Provides-Extra: doctr
Requires-Dist: pyclipper==1.3.0.post4; extra == "doctr"
Requires-Dist: shapely==2.0.1; extra == "doctr"
Requires-Dist: tqdm>=4; extra == "doctr"
Provides-Extra: lint
Requires-Dist: flake8==5.0.4; extra == "lint"
Requires-Dist: flake8-absolute-import==1.0.0.1; extra == "lint"
Requires-Dist: flake8-annotations==2.9.1; extra == "lint"
Requires-Dist: flake8-bugbear==23.3.12; extra == "lint"
Requires-Dist: flake8-builtins==2.1.0; extra == "lint"
Requires-Dist: flake8-clean-block==0.1.2; extra == "lint"
Requires-Dist: flake8-fill-one-line>=0.4.0; extra == "lint"
Requires-Dist: flake8-import-order==0.18.2; extra == "lint"
Requires-Dist: flake8-multiline-containers==0.0.19; extra == "lint"
Requires-Dist: flake8-print==5.0.0; extra == "lint"
Requires-Dist: flake8-quotes==3.3.2; extra == "lint"
Requires-Dist: flake8-use-fstring==1.4; extra == "lint"
Requires-Dist: pycodestyle==2.9.0; extra == "lint"
Requires-Dist: pep8-naming==0.13.3; extra == "lint"
Provides-Extra: torch
Requires-Dist: torch~=1.11.0; extra == "torch"
Requires-Dist: torchvision~=0.12.0; extra == "torch"
